Workbook

Sheet Summary
A1: Copilot CLI vs Claude Code CLI — Output Comparator batch
A2: 55 prompts run through the app's /api/compare endpoint. System prompt: software-assistant.md. Scores are the app's own 0–100 metrics; Winner = higher Overall, Tie if within 3 points (app rule).
A4: Metric | B4: GitHub Copilot CLI | C4: Claude Code CLI
A5: Prompts run | B5: =COUNT(Results!$A$2:$A$56) -> 55 | C5: =COUNT(Results!$A$2:$A$56) -> 55
A6: Wins | B6: =COUNTIF(Results!$T$2:$T$56,"Copilot") -> 1 | C6: =COUNTIF(Results!$T$2:$T$56,"Claude") -> 54
A7: Ties | B7: =COUNTIF(Results!$T$2:$T$56,"Tie") -> 0 | C7: =COUNTIF(Results!$T$2:$T$56,"Tie") -> 0
A8: Failed runs | B8: =COUNTIF(Results!$K$2:$K$56,"Failed") -> 0 | C8: =COUNTIF(Results!$S$2:$S$56,"Failed") -> 0
A9: Avg Overall | B9: =AVERAGE(Results!$J$2:$J$56) -> 55.090909 | C9: =AVERAGE(Results!$R$2:$R$56) -> 66.818182
A10: Avg Quality | B10: =AVERAGE(Results!$F$2:$F$56) -> 98.636364 | C10: =AVERAGE(Results!$N$2:$N$56) -> 99.363636
A11: Avg Accuracy | B11: =AVERAGE(Results!$G$2:$G$56) -> 6.6 | C11: =AVERAGE(Results!$O$2:$O$56) -> 6.3272727
A12: Avg Speed score | B12: =AVERAGE(Results!$H$2:$H$56) -> 21.454545 | C12: =AVERAGE(Results!$P$2:$P$56) -> 98.545455
A13: Avg Length score | B13: =AVERAGE(Results!$I$2:$I$56) -> 100 | C13: =AVERAGE(Results!$Q$2:$Q$56) -> 100
A14: Avg latency (s) | B14: =AVERAGE(Results!$D$2:$D$56) -> 23.287273 | C14: =AVERAGE(Results!$L$2:$L$56) -> 15.247273
A15: Median latency (s) | B15: =MEDIAN(Results!$D$2:$D$56) -> 21.3 | C15: =MEDIAN(Results!$L$2:$L$56) -> 14.6
A16: Avg words | B16: =AVERAGE(Results!$E$2:$E$56) -> 204.18182 | C16: =AVERAGE(Results!$M$2:$M$56) -> 236.30909
A17: Faster on (prompts) | B17: =SUMPRODUCT(--(Results!$D$2:$D$56<Results!$L$2:$L$56)) -> 1 | C17: =SUMPRODUCT(--(Results!$L$2:$L$56<Results!$D$2:$D$56)) -> 54
A19: Category | B19: Prompts | C19: Copilot avg Overall | D19: Claude avg Overall | E19: Copilot wins | F19: Claude wins | G19: Ties
A20: Architecture | B20: =COUNTIF(Results!$B$2:$B$56,$A20) -> 5 | C20: =AVERAGEIFS(Results!$J$2:$J$56,Results!$B$2:$B$56,$A20) -> 54.6 | D20: =AVERAGEIFS(Results!$R$2:$R$56,Results!$B$2:$B$56,$A20) -> 67 | E20: =COUNTIFS(Results!$B$2:$B$56,$A20,Results!$T$2:$T$56,"Copilot") -> 0 | F20: =COUNTIFS(Results!$B$2:$B$56,$A20,Results!$T$2:$T$56,"Claude") -> 5 | G20: =COUNTIFS(Results!$B$2:$B$56,$A20,Results!$T$2:$T$56,"Tie") -> 0
A21: Python | B21: =COUNTIF(Results!$B$2:$B$56,$A21) -> 5 | C21: =AVERAGEIFS(Results!$J$2:$J$56,Results!$B$2:$B$56,$A21) -> 54.4 | D21: =AVERAGEIFS(Results!$R$2:$R$56,Results!$B$2:$B$56,$A21) -> 67.4 | E21: =COUNTIFS(Results!$B$2:$B$56,$A21,Results!$T$2:$T$56,"Copilot") -> 0 | F21: =COUNTIFS(Results!$B$2:$B$56,$A21,Results!$T$2:$T$56,"Claude") -> 5 | G21: =COUNTIFS(Results!$B$2:$B$56,$A21,Results!$T$2:$T$56,"Tie") -> 0
A22: JavaScript/TypeScript | B22: =COUNTIF(Results!$B$2:$B$56,$A22) -> 5 | C22: =AVERAGEIFS(Results!$J$2:$J$56,Results!$B$2:$B$56,$A22) -> 55.8 | D22: =AVERAGEIFS(Results!$R$2:$R$56,Results!$B$2:$B$56,$A22) -> 68.2 | E22: =COUNTIFS(Results!$B$2:$B$56,$A22,Results!$T$2:$T$56,"Copilot") -> 0 | F22: =COUNTIFS(Results!$B$2:$B$56,$A22,Results!$T$2:$T$56,"Claude") -> 5 | G22: =COUNTIFS(Results!$B$2:$B$56,$A22,Results!$T$2:$T$56,"Tie") -> 0
A23: Debugging | B23: =COUNTIF(Results!$B$2:$B$56,$A23) -> 5 | C23: =AVERAGEIFS(Results!$J$2:$J$56,Results!$B$2:$B$56,$A23) -> 55.6 | D23: =AVERAGEIFS(Results!$R$2:$R$56,Results!$B$2:$B$56,$A23) -> 67.4 | E23: =COUNTIFS(Results!$B$2:$B$56,$A23,Results!$T$2:$T$56,"Copilot") -> 0 | F23: =COUNTIFS(Results!$B$2:$B$56,$A23,Results!$T$2:$T$56,"Claude") -> 5 | G23: =COUNTIFS(Results!$B$2:$B$56,$A23,Results!$T$2:$T$56,"Tie") -> 0
A24: SQL & Data | B24: =COUNTIF(Results!$B$2:$B$56,$A24) -> 5 | C24: =AVERAGEIFS(Results!$J$2:$J$56,Results!$B$2:$B$56,$A24) -> 55.6 | D24: =AVERAGEIFS(Results!$R$2:$R$56,Results!$B$2:$B$56,$A24) -> 67.4 | E24: =COUNTIFS(Results!$B$2:$B$56,$A24,Results!$T$2:$T$56,"Copilot") -> 0 | F24: =COUNTIFS(Results!$B$2:$B$56,$A24,Results!$T$2:$T$56,"Claude") -> 5 | G24: =COUNTIFS(Results!$B$2:$B$56,$A24,Results!$T$2:$T$56,"Tie") -> 0
A25: DevOps & Cloud | B25: =COUNTIF(Results!$B$2:$B$56,$A25) -> 5 | C25: =AVERAGEIFS(Results!$J$2:$J$56,Results!$B$2:$B$56,$A25) -> 56.2 | D25: =AVERAGEIFS(Results!$R$2:$R$56,Results!$B$2:$B$56,$A25) -> 67.8 | E25: =COUNTIFS(Results!$B$2:$B$56,$A25,Results!$T$2:$T$56,"Copilot") -> 0 | F25: =COUNTIFS(Results!$B$2:$B$56,$A25,Results!$T$2:$T$56,"Claude") -> 5 | G25: =COUNTIFS(Results!$B$2:$B$56,$A25,Results!$T$2:$T$56,"Tie") -> 0
A26: Security | B26: =COUNTIF(Results!$B$2:$B$56,$A26) -> 5 | C26: =AVERAGEIFS(Results!$J$2:$J$56,Results!$B$2:$B$56,$A26) -> 55 | D26: =AVERAGEIFS(Results!$R$2:$R$56,Results!$B$2:$B$56,$A26) -> 66.8 | E26: =COUNTIFS(Results!$B$2:$B$56,$A26,Results!$T$2:$T$56,"Copilot") -> 0 | F26: =COUNTIFS(Results!$B$2:$B$56,$A26,Results!$T$2:$T$56,"Claude") -> 5 | G26: =COUNTIFS(Results!$B$2:$B$56,$A26,Results!$T$2:$T$56,"Tie") -> 0
A27: Algorithms | B27: =COUNTIF(Results!$B$2:$B$56,$A27) -> 5 | C27: =AVERAGEIFS(Results!$J$2:$J$56,Results!$B$2:$B$56,$A27) -> 53.4 | D27: =AVERAGEIFS(Results!$R$2:$R$56,Results!$B$2:$B$56,$A27) -> 65.4 | E27: =COUNTIFS(Results!$B$2:$B$56,$A27,Results!$T$2:$T$56,"Copilot") -> 0 | F27: =COUNTIFS(Results!$B$2:$B$56,$A27,Results!$T$2:$T$56,"Claude") -> 5 | G27: =COUNTIFS(Results!$B$2:$B$56,$A27,Results!$T$2:$T$56,"Tie") -> 0
A28: API Design | B28: =COUNTIF(Results!$B$2:$B$56,$A28) -> 5 | C28: =AVERAGEIFS(Results!$J$2:$J$56,Results!$B$2:$B$56,$A28) -> 55.4 | D28: =AVERAGEIFS(Results!$R$2:$R$56,Results!$B$2:$B$56,$A28) -> 64.6 | E28: =COUNTIFS(Results!$B$2:$B$56,$A28,Results!$T$2:$T$56,"Copilot") -> 1 | F28: =COUNTIFS(Results!$B$2:$B$56,$A28,Results!$T$2:$T$56,"Claude") -> 4 | G28: =COUNTIFS(Results!$B$2:$B$56,$A28,Results!$T$2:$T$56,"Tie") -> 0
A29: Git & Tooling | B29: =COUNTIF(Results!$B$2:$B$56,$A29) -> 5 | C29: =AVERAGEIFS(Results!$J$2:$J$56,Results!$B$2:$B$56,$A29) -> 55.6 | D29: =AVERAGEIFS(Results!$R$2:$R$56,Results!$B$2:$B$56,$A29) -> 67.2 | E29: =COUNTIFS(Results!$B$2:$B$56,$A29,Results!$T$2:$T$56,"Copilot") -> 0 | F29: =COUNTIFS(Results!$B$2:$B$56,$A29,Results!$T$2:$T$56,"Claude") -> 5 | G29: =COUNTIFS(Results!$B$2:$B$56,$A29,Results!$T$2:$T$56,"Tie") -> 0
A30: Tech Writing | B30: =COUNTIF(Results!$B$2:$B$56,$A30) -> 5 | C30: =AVERAGEIFS(Results!$J$2:$J$56,Results!$B$2:$B$56,$A30) -> 54.4 | D30: =AVERAGEIFS(Results!$R$2:$R$56,Results!$B$2:$B$56,$A30) -> 65.8 | E30: =COUNTIFS(Results!$B$2:$B$56,$A30,Results!$T$2:$T$56,"Copilot") -> 0 | F30: =COUNTIFS(Results!$B$2:$B$56,$A30,Results!$T$2:$T$56,"Claude") -> 5 | G30: =COUNTIFS(Results!$B$2:$B$56,$A30,Results!$T$2:$T$56,"Tie") -> 0
A32: Notes
A33: • Speed score is relative between the two agents on each prompt: the faster one gets 100, the slower ~20, regardless of the gap size.
A34: • Accuracy is TF-IDF word overlap between prompt and answer (not correctness); values of 5–15 are normal for good answers.
A35: • Failed runs (auth errors, timeouts) score 0 on every metric.
A36: • Claude Code CLI ran with --permission-mode acceptEdits; Copilot CLI with --allow-all. Both got the identical prompt text.

Sheet Results
A1: # | B1: Category | C1: Prompt | D1: Copilot Latency (s) | E1: Copilot Words | F1: Copilot Quality | G1: Copilot Accuracy | H1: Copilot Speed | I1: Copilot Length | J1: Copilot Overall | K1: Copilot Status | L1: Claude Latency (s) | M1: Claude Words | N1: Claude Quality | O1: Claude Accuracy | P1: Claude Speed | Q1: Claude Length | R1: Claude Overall | S1: Claude Status | T1: Winner | U1: Copilot answer | V1: Claude answer
A2: 1 | B2: Architecture | C2: Compare monolith vs microservices for an e-commerce platform with 1 million users and recommend one. | D2: 28.1 | E2: 242 | F2: 100 | G2: 9 | H2: 20 | I2: 100 | J2: 56 | K2: OK | L2: 19.8 | M2: 235 | N2: 100 | O2: 7 | P2: 100 | Q2: 100 | R2: 68 | S2: OK | T2: =IF(ABS(J2-R2)<=3,"Tie",IF(J2>R2,"Copilot","Claude")) -> Claude | U2: Recommendation — short summary - For an e‑commerce platform with ~1M users, start with a well‑designed modular monolith and evolve to microservices selectively. It balances time‑to‑market, operational risk and cost while preserving a clear migration path. Comparison (concise) - Development speed & complexity - Monolith: Faster to implement, simpler local debugging and end‑to‑end testing. - Microservices: More complex (networking, contracts, deployments); slower feature delivery initially. - Scalability & performance - Monolith: Can scale vertically or via process replication; simpler caching and DB transactions. - Microservices: Better for scaling hotspots independently (e.g., catalog, checkout) but adds network latency and coordination. - Data consistency - Monolith: Strong ACID transactions easier. - Microservices: Eventual consistency common; requires careful design for orders/payments. - Operations & cost - Monolith: Lower infra/ops overhead. - Microservices: Higher operational burden (service discovery, observability, tracing, CI/CD) — requires mature SRE/DevOps. - Resilience & ownership - Monolith: Single failure domain unless designed with isolation patterns. - Microservices: Failure isolation, independent deploys, clear team ownership. When microservices make sense - Large autonomous teams, proven traffic hotspots, strict SLAs, or need for polyglot stacks and independent scaling. Practical migration path - Build a modular monolith with clear bounded contexts (catalog, cart, orders, payments). - Invest in good CI/CD, tests, observability and domain events. - Extract services iteratively (strangler pattern) only for justified bottlenecks. Trade‑offs - Choosing monolith delays operational complexity and reduces early cost; microservices optimize long‑term scale/independence at higher short‑term cost and risk. | V2: ## Monolith vs Microservices for E-Commerce (1M Users) ### Monolith **Pros:** - Simpler to develop, test, and deploy initially - Lower operational overhead (one deployable, one DB) - Easier debugging — single process, no network hops **Cons:** - Scaling is all-or-nothing; you can't scale checkout independently of catalog - Deploys become risky as the codebase grows — one bad merge affects everything - Team coupling increases; multiple squads stepping on each other ### Microservices **Pros:** - Independent scaling (checkout, inventory, search can scale separately) - Independent deploys reduce blast radius - Teams own services end-to-end, enabling faster iteration **Cons:** - Significant operational complexity (service mesh, distributed tracing, eventual consistency) - Network latency and partial-failure handling - Requires mature CI/CD, observability, and on-call culture ### Recommendation: **Start modular monolith, extract incrementally** At 1M users, a well-structured **modular monolith** handles the load comfortably (vertical + horizontal scaling behind a load balancer). Organize code into bounded modules (catalog, orders, payments, users) with clear internal APIs. Extract to microservices **only when you hit a concrete bottleneck** — e.g., search needs its own scaling profile, or the payments team's deploy cadence is blocked by catalog changes. ### Why not jump straight to microservices? Most e-commerce platforms at this scale don't need them yet, and the operational tax (Kubernetes, service discovery, distributed transactions) is steep. Premature decomposition is harder to undo than extracting a service later from a clean module boundary.
A3: 2 | B3: Architecture | C3: Explain the cache-aside pattern and when to use it. | D3: 35.2 | E3: 256 | F3: 100 | G3: 7 | H3: 20 | I3: 100 | J3: 55 | K3: OK | L3: 15.1 | M3: 252 | N3: 100 | O3: 7 | P3: 100 | Q3: 100 | R3: 67 | S3: OK | T3: =IF(ABS(J3-R3)<=3,"Tie",IF(J3>R3,"Copilot","Claude")) -> Claude | U3: What it is - Cache-aside (lazy loading) keeps the cache empty until data is requested. The application is responsible for reading/writing both cache and backing store. Read + write flow - Read: 1. Try cache.get(key). 2. If hit → return. 3. If miss → load from DB, cache.set(key, value, ttl), return. - Write: - Update DB, then invalidate/delete cache key (or update cache afterwards). - Never rely on cache as the source of truth. When to use it - Read-heavy workloads with expensive reads (complex queries, aggregations). - Data where eventual consistency is acceptable (slight staleness tolerated). - Simple caching needs without strong transactional requirements. Benefits - Simple to implement. - Avoids caching cold/wasted entries. - Keeps DB as authoritative source. Trade-offs and pitfalls - Stale reads between DB write and cache invalidation if done incorrectly. - Cache stampede on popular keys after expiry (use locks/request coalescing). - Extra complexity on writes (must invalidate or update cache). - Not suitable when strong read-after-write consistency is required. Best practices - Use short TTLs for volatile data and negative caching for misses. - Use atomic operations / distributed locks to avoid stampedes (e.g., singleflight). - Monitor cache hit rate and misses; design stable cache keys. - For strict consistency consider write-through or read-repair alternatives. Example (pseudocode) - Read: def get(k): v = cache.get(k) if v: return v v = db.get(k) if v is None: cache.set(k, NULL, short_ttl); return None cache.set(k, v, ttl); return v - Update: def update(k, v): db.update(k, v) cache.delete(k) # invalidate so next read repopulates | V3: ## Cache-Aside Pattern Cache-aside (also called **lazy-loading**) is a caching strategy where the application manages the cache explicitly, rather than the cache being updated automatically by the data store. ### How it works 1. **Read path:** Check the cache first. On a **hit**, return the cached value. On a **miss**, read from the data store, populate the cache, then return the value. 2. **Write path:** Write directly to the data store, then **invalidate** (or delete) the corresponding cache entry. The next read will repopulate it. ``` value = cache.get(key) if value is None: value = db.query(key) cache.set(key, value, ttl=300) return value ``` ### When to use it - **Read-heavy workloads** where the same data is fetched repeatedly. - **Data that tolerates brief staleness** — there's always a window between a DB write and cache invalidation where stale data can be served. - When you need **fine-grained control** over what gets cached and for how long. ### Trade-offs | Pro | Con | |---|---| | Simple to implement | Cold-start / cache-miss penalty | | Only caches data that's actually requested | Risk of stale reads under race conditions | | Works with any backing store | Application owns all caching logic | ### Alternatives to consider - **Write-through** — if you need strong consistency between cache and store. - **Write-behind** — if you want to absorb write bursts at the cost of durability risk. Cache-aside is the most common pattern in practice (e.g., Redis + PostgreSQL) because of its simplicity and flexibility.
A4: 3 | B4: Architecture | C4: How would you design a URL shortener that handles 10,000 requests per second? | D4: 33.9 | E4: 317 | F4: 100 | G4: 2 | H4: 20 | I4: 100 | J4: 54 | K4: OK | L4: 21.1 | M4: 299 | N4: 100 | O4: 4 | P4: 100 | Q4: 100 | R4: 66 | S4: OK | T4: =IF(ABS(J4-R4)<=3,"Tie",IF(J4>R4,"Copilot","Claude")) -> Claude | U4: Overview - Goal: reliable, low-latency redirect and scalable create API at 10k RPS. Read-heavy design with caches, partitioned storage, and simple unique-key generation. Architecture (high level) - Edge: CDN for redirect caching (HTTP 301/302). Global PoPs reduce latency and origin load. - API tier: stateless autoscaled app servers behind LB for create/management APIs. - Cache: multi-layer — CDN → Redis cluster (hot keys) → persistent store. - Persistent store: partitioned key-value DB (Cassandra / DynamoDB / CockroachDB) for high write/read throughput and geo-replication. - Analytics/events: async ingestion (Kafka) -> processing/warehouse. Data model - ShortKey (PK) -> { original_url, created_at, owner_id, ttl, is_custom, metadata }. - Use compact key size (6–8 base62 chars). Key generation - Option A (sequential + obfuscate): Snowflake/ULID -> base62 encode -> deterministic, collision-free, monotonic. - Option B (random): cryptographic random 6–8 chars + check-write CAS => slight extra write but unpredictable. - Trade-off: sequential is predictable (analytics linkability) but faster/no-checks; random gives privacy at cost of potential retries. Read path (redirect) - CDN serves cached redirects. Miss -> API -> Redis -> DB. Redis TTL ~ 1h and write-through on create. - Use HTTP 301 to allow long CDN caching for permanent links. Write path (create) - Validate URL, rate-limit, ACLs. Generate key, attempt Redis & DB write (DB as source of truth). - If analytics needed, publish event to Kafka. Scaling & availability - Partition keys with consistent hashing or natural partition from base62 mapping. - Deploy multi-AZ, monitor latency/error budgets, autoscale API and Redis. - Backup DB snapshots; use leaderless storage or quorum writes for availability. Security & anti-abuse - Rate limiting, CAPTCHA for suspected bots, domain allow/block lists, sanitized redirects (no open-redirect abuse). Minimal code (base62 encode) - Python: def base62(n): chars="0123456789abcdefghijklmnopqrstuvwxyzABCDEFGHIJKLMNOPQRSTUVWXYZ" s=""; while n: s=chars[n%62]+s; n//=62 return s or "0" Trade-offs - CDN+cache reduces cost/latency; increases eventual consistency window for recent creates. Sequential IDs simpler/cheaper; random keys more private. | V4: # URL Shortener at 10K RPS ## Core Architecture **Write path** (create short URL): Client → Load Balancer → API Server → Database + Cache **Read path** (redirect): Client → Load Balancer → API Server → Cache (→ DB on miss) → 301/302 Redirect Reads dominate (~100:1), so optimize heavily for lookups. ## Key Generation Use a **base62-encoded counter** (a-z, A-Z, 0-9). A 7-character key gives ~3.5 trillion unique URLs. Two approaches: - **Pre-generated key pool**: A background service fills a key table; API servers claim ranges in batches. Avoids collision entirely. - **Hash + truncate**: MD5/SHA256 the long URL, take the first 7 chars. Requires collision handling. The pre-generated approach is simpler under high concurrency. ## Storage & Caching - **Database**: A partitioned key-value store (DynamoDB, Cassandra, or sharded PostgreSQL). Partition by short-key hash for even distribution. - **Cache**: Redis cluster in front of the DB. At 10K RPS with a ~95% cache hit rate, only ~500 RPS reach the database. - **TTL policy**: Cache hot URLs for 24h; evict LRU for cold ones. ## Scaling Considerations - **Stateless API servers** behind an L7 load balancer — scale horizontally. - **Read replicas** for the DB to absorb cache misses. - **Rate limiting** per API key to prevent abuse. - **Analytics** (click counts, geo, referrer): write to Kafka → async consumers, not in the hot path. ## Trade-offs | Decision | Pro | Con | |---|---|---| | 301 (permanent) redirect | Client caches, fewer hits | Lose analytics visibility | | 302 (temporary) redirect | Every click tracked | Higher server load | | Custom alias support | Better UX | Collision checks, larger key space | For 10K RPS, the combination of Redis caching, stateless horizontal scaling, and a partitioned data store keeps latency under 10ms at p99.
A5: 4 | B5: Architecture | C5: When should a team choose event-driven architecture over request-response? Give trade-offs. | D5: 19.2 | E5: 120 | F5: 100 | G5: 4 | H5: 20 | I5: 100 | J5: 54 | K5: OK | L5: 17.4 | M5: 272 | N5: 100 | O5: 8 | P5: 100 | Q5: 100 | R5: 68 | S5: OK | T5: =IF(ABS(J5-R5)<=3,"Tie",IF(J5>R5,"Copilot","Claude")) -> Claude | U5: When to choose event-driven - Use when services must be loosely coupled, scale independently, or process asynchronous workflows (e.g., order pipelines, analytics, notifications). - Good for real-time fan‑out, integrations, long-running/background work, audit trails, CQRS/async read models. - Prefer when eventual consistency is acceptable. When to prefer request–response - Simple CRUD or synchronous user interactions requiring immediate, strongly consistent responses. - Low operational complexity, predictable latency, simpler error handling and testing. Trade-offs (summary) - Pros: decoupling, horizontal scalability, resilience to partial failures, natural fan‑out, better throughput. - Cons: higher operational and architectural complexity, distributed debugging/tracing, eventual consistency, message ordering/duplication concerns, harder transactional semantics, testing overhead and often higher infra cost. Quick example // publish bus.publish('order.created', order) // sync call http.post('/orders', order) | V5: ## When to Choose Event-Driven Over Request-Response **Choose event-driven when:** - **Multiple consumers** need to react to the same action (e.g., order placed → inventory, billing, notifications all respond independently). - **Temporal decoupling** matters — the producer shouldn't block waiting for downstream systems, or those systems may be temporarily unavailable. - **Load leveling** is needed — a queue/broker absorbs traffic spikes so consumers process at their own pace. - **You need extensibility** — new consumers can subscribe without modifying the producer. **Stick with request-response when:** - You need an **immediate, synchronous answer** (e.g., "is this username available?"). - The interaction is **simple and between two parties** with low latency requirements. - **Strong consistency** is required in a single operation (e.g., a bank transfer that must succeed or fail atomically). ## Trade-offs | | Event-Driven | Request-Response | |---|---|---| | **Coupling** | Loose — producers don't know consumers | Tight — caller knows the callee | | **Consistency** | Eventual; harder to reason about | Immediate; easier transactional guarantees | | **Debugging** | Harder — distributed traces, out-of-order events | Easier — linear call stack | | **Scalability** | Naturally scales via partitioned consumers | Scales by adding replicas behind a load balancer | | **Infrastructure** | Requires a broker (Kafka, SQS, etc.) — operational overhead | Simpler infra (HTTP/gRPC) | | **Error handling** | Dead-letter queues, retries, idempotency required | Standard try/catch or status codes | **Rule of thumb:** If you're drawing arrows from one box to many, or you need resilience to downstream failures, go event-driven. If it's a simple "ask and get an answer" flow, request-response is simpler and sufficient.
A6: 5 | B6: Architecture | C6: Explain the CQRS pattern with a concrete example and its downsides. | D6: 19.3 | E6: 215 | F6: 100 | G6: 4 | H6: 20 | I6: 100 | J6: 54 | K6: OK | L6: 17.4 | M6: 260 | N6: 100 | O6: 2 | P6: 100 | Q6: 100 | R6: 66 | S6: OK | T6: =IF(ABS(J6-R6)<=3,"Tie",IF(J6>R6,"Copilot","Claude")) -> Claude | U6: Overview: - CQRS (Command Query Responsibility Segregation) splits a system into two parts: commands (writes/changes) and queries (reads). Each side can use different models, storage, and scaling. Concrete example — e-commerce Orders: - Write side: Accepts commands like PlaceOrder, CancelOrder. Validates business rules and updates the canonical order store (normalized). - Read side: Builds denormalized views for UI (OrderSummary, OrderHistory) optimized for fast queries and paging, often via projections or materialized views. - Pattern often paired with Event Sourcing (writes produce events; read models subscribe and project). Architecture (high level): - Command handlers -> domain model -> persistent store / events - Events or change stream -> projection workers -> read database(s) - Query handlers read from read-optimized DB Mini code sketch (pseudo-C#): ```csharp // Command await commandBus.Send(new PlaceOrderCmd(customerId, items)); // Query var page = await queryService.GetOrdersForCustomer(customerId, page, size); ``` Downsides / trade-offs: - Complexity: more moving parts (handlers, projections, messaging). - Eventual consistency: reads may lag after writes; UI/UX must handle that. - Data duplication & operational overhead: multiple databases and synchronization code. - Harder testing and debugging (race conditions, projection bugs). - Overkill for simple CRUD apps. When to use: - High read/write scalability needs, complex domain rules, or when read models differ dramatically from write models. Otherwise stick with simpler layered/CRUD designs. | V6: ## CQRS (Command Query Responsibility Segregation) CQRS splits your application's data model into two sides: a **write model** (commands) that handles state changes, and a **read model** (queries) optimized for data retrieval. ### Concrete Example: E-Commerce Order System **Write side** — A `PlaceOrderCommand` validates inventory, applies business rules, and persists an `Order` aggregate to a normalized relational schema. ``` PlaceOrderCommand → OrderCommandHandler → Orders table (normalized) ``` **Read side** — A `GetOrderSummaryQuery` reads from a denormalized `OrderSummaryView` table pre-joined with customer and product data, optimized for fast lookups. ``` GetOrderSummaryQuery → OrderQueryHandler → OrderSummaryView (denormalized) ``` A background projector/sync process keeps the read model updated whenever the write side changes. This is often event-driven (pairs naturally with Event Sourcing, though they're independent patterns). ### Benefits - **Independent scaling** — read-heavy workloads (common) scale separately from writes - **Optimized schemas** — each side uses the storage shape best suited to its job - **Simpler models** — command handlers focus on invariants; query handlers focus on presentation ### Downsides - **Eventual consistency** — the read model lags behind writes, which complicates UX (e.g., "I just placed an order but don't see it") - **Operational complexity** — two data stores, sync infrastructure, failure handling for projections - **Overkill for simple domains** — a basic CRUD app gains little but pays the full complexity cost - **Debugging difficulty** — tracing a bug across command/event/projection boundaries is harder than in a single model **Rule of thumb:** reach for CQRS when read and write patterns diverge significantly in shape, scale, or complexity — not by default.
A7: 6 | B7: Python | C7: Show a Python function that removes duplicates from a list while preserving order, and explain its complexity. | D7: 23.7 | E7: 166 | F7: 100 | G7: 5 | H7: 20 | I7: 100 | J7: 55 | K7: OK | L7: 13 | M7: 189 | N7: 100 | O7: 6 | P7: 100 | Q7: 100 | R7: 67 | S7: OK | T7: =IF(ABS(J7-R7)<=3,"Tie",IF(J7>R7,"Copilot","Claude")) -> Claude | U7: Function ```python def remove_duplicates_preserve_order(seq): seen = set() out = [] for item in seq: if item not in seen: seen.add(item) out.append(item) return out ``` Notes and complexity - Time: O(n) on average — each membership test and add on a hash set is O(1) average, so linear over n items. - Space: O(n) extra for the `seen` set and the output list. - Order: Stable — the first occurrence of each element is kept in original order. - Trade-offs: - Elements must be hashable. For hashable-only input, a shorter equivalent is `list(dict.fromkeys(seq))` (also O(n)). - If elements may be unhashable (e.g., lists), fallback is to track seen items in a list and check with `if item not in seen`, which is O(n^2) time but handles all types. - For large unhashable items, consider converting elements to a stable hashable representation (tuple, JSON string, or pickle) — this adds conversion cost and potential collisions/serialization caveats. Use the hashable approach when possible for best performance and memory/time trade-off. | V7: ## Removing Duplicates While Preserving Order ```python def remove_duplicates(items): seen = set() result = [] for item in items: if item not in seen: seen.add(item) result.append(item) return result ``` **Usage:** ```python >>> remove_duplicates([3, 1, 2, 3, 1, 4]) [3, 1, 2, 4] ``` ### Complexity - **Time: O(n)** — single pass over the list; `set` lookups and insertions are O(1) amortized. - **Space: O(n)** — worst case every element is unique, so both `seen` and `result` hold *n* items. ### Alternatives & Trade-offs | Approach | Preserves order? | Time | Notes | |---|---|---|---| | `dict.fromkeys(items)` | Yes (Python 3.7+) | O(n) | One-liner, same complexity, but less explicit. | | `list(set(items))` | **No** | O(n) | Simplest, but order is lost. | | Nested loop (`if x not in result`) | Yes | O(n²) | No extra set, but `in` on a list is O(n). | The `set`-based approach above is the standard choice — it's clear, efficient, and works with any hashable element type. If you need to handle unhashable items (e.g., dicts), you'd fall back to the O(n²) list-check or serialize items to a hashable form.
A8: 7 | B8: Python | C8: Explain the difference between a list, tuple, set and dict in Python with one example each. | D8: 18.5 | E8: 103 | F8: 100 | G8: 6 | H8: 20 | I8: 100 | J8: 55 | K8: OK | L8: 13 | M8: 235 | N8: 100 | O8: 7 | P8: 100 | Q8: 100 | R8: 68 | S8: OK | T8: =IF(ABS(J8-R8)<=3,"Tie",IF(J8>R8,"Copilot","Claude")) -> Claude | U8: Python collections — quick comparison - List — ordered, mutable, allows duplicates. Good for sequences you change. Example: my_list = [1, 2, 2] - Tuple — ordered, immutable, allows duplicates. Use for fixed records or hashable grouping. Example: my_tuple = (1, 2, 2) - Set — unordered, mutable, no duplicates. Fast membership, good for dedup and set ops. Example: my_set = {1, 2} # duplicate values collapse - Dict — mapping key→value, keys unique, mutable. Fast lookup by key; insertion-ordered (Py3.7+). Example: my_dict = {'a': 1, 'b': 2} Trade-offs: lists/tuples preserve order (tuples lighter, immutable); sets/dicts give O(1) membership/lookup vs O(n) for lists. | V8: ## Python Collection Types ### List — ordered, mutable, allows duplicates ```python fruits = ["apple", "banana", "apple"] fruits.append("cherry") # ["apple", "banana", "apple", "cherry"] ``` Use when you need an ordered sequence you'll modify over time. ### Tuple — ordered, immutable, allows duplicates ```python point = (3, 7) x, y = point # unpacking: x=3, y=7 ``` Use for fixed records (coordinates, DB rows, dict keys). Immutability makes tuples hashable and slightly faster than lists. ### Set — unordered, mutable, **no duplicates** ```python tags = {"python", "java", "python"} print(tags) # {"python", "java"} — duplicate removed ``` Use for membership tests (`in` is O(1)), deduplication, and set operations (union, intersection). ### Dict — ordered (3.7+), mutable, key-value pairs ```python user = {"name": "Alice", "age": 30} user["email"] = "alice@example.com" # add a new key ``` Use when you need fast lookup by a meaningful key. ### Quick Comparison | Feature | List | Tuple | Set | Dict | |---------|------|-------|-----|------| | Ordered | yes | yes | no | yes* | | Mutable | yes | **no** | yes | yes | | Duplicates | yes | yes | **no** | keys: no | | Lookup | O(n) | O(n) | O(1) | O(1) by key | *Insertion-ordered since Python 3.7. **Rule of thumb:** default to a list; reach for a tuple when immutability matters, a set when uniqueness/membership matters, and a dict when you need key-based access.
A9: 8 | B9: Python | C9: How do Python decorators work? Show a timing decorator example. | D9: 25.1 | E9: 190 | F9: 85 | G9: 7 | H9: 20 | I9: 100 | J9: 51 | K9: OK | L9: 12.4 | M9: 181 | N9: 100 | O9: 5 | P9: 100 | Q9: 100 | R9: 67 | S9: OK | T9: =IF(ABS(J9-R9)<=3,"Tie",IF(J9>R9,"Copilot","Claude")) -> Claude | U9: How decorators work - A decorator is a callable that takes a function (or method) and returns a new callable. - Common pattern: a decorator returns a wrapper closure that calls the original function and can run code before/after it. - Use functools.wraps on the wrapper to preserve the original function’s metadata (name, docstring, signature). - Decorators can be stacked, take arguments (returning a decorator), applied to methods (self is passed normally), or implemented as classes. - Trade-offs: small runtime overhead, not suitable for microbenchmarks; be careful with async functions (need async wrapper) and with preserving signatures if introspection matters. Timing decorator example - Measures elapsed time safely even on exception using finally; uses time.perf_counter for high-resolution timing. Code: import time, functools def timing(func): @functools.wraps(func) def wrapper(*args, **kwargs): start = time.perf_counter() try: return func(*args, **kwargs) finally: elapsed = time.perf_counter() - start print(f"{func.__name__} took {elapsed:.6f}s") return wrapper @timing def work(n): sum(i*i for i in range(n)) work(1000000) # prints: work took 0.0xxxxx s Notes - For async functions, make wrapper async and await the call. - For configurable output (e.g., logging instead of print) write a decorator factory: def timing(logger=None): return decorator. | V9: ## Python Decorators A decorator is a function that **wraps another function** to extend its behavior without modifying it. When you write `@decorator` above a function definition, Python essentially does: ```python func = decorator(func) ``` The decorator receives the original function, defines an inner wrapper that adds logic before/after calling it, and returns the wrapper. ### Timing Decorator Example ```python import time import functools def timer(func): @functools.wraps(func) # preserves original name/docstring def wrapper(*args, **kwargs): start = time.perf_counter() result = func(*args, **kwargs) elapsed = time.perf_counter() - start print(f"{func.__name__} took {elapsed:.4f}s") return result return wrapper @timer def slow_add(a, b): time.sleep(1) return a + b slow_add(2, 3) # prints: slow_add took 1.00xxs ``` ### Key points - **`functools.wraps`** — always use it so introspection (`__name__`, `__doc__`, `help()`) reflects the original function, not the wrapper. - **`*args, **kwargs`** — makes the wrapper generic so it works on any signature. - **Stacking** — decorators compose bottom-up: `@a @b def f` means `f = a(b(f))`. - **Parameterized decorators** — if you need arguments (e.g., `@timer(unit="ms")`), add another nesting level: a factory function that returns the actual decorator.
A10: 9 | B10: Python | C10: Explain Python's GIL and how it affects multithreading vs multiprocessing. | D10: 28.9 | E10: 234 | F10: 100 | G10: 8 | H10: 20 | I10: 100 | J10: 56 | K10: OK | L10: 16.1 | M10: 248 | N10: 100 | O10: 7 | P10: 100 | Q10: 100 | R10: 68 | S10: OK | T10: =IF(ABS(J10-R10)<=3,"Tie",IF(J10>R10,"Copilot","Claude")) -> Claude | U10: What is the GIL? - GIL = Global Interpreter Lock (in CPython): a process-wide mutex that ensures only one native thread executes Python bytecode at a time. - Rationale: simplifies memory management (reference counting) and makes many single-threaded C extensions easier to implement. Effect on multithreading - CPU-bound work: threads cannot run Python bytecode in parallel because of the GIL → no CPU speedup from multiple threads; context switches still cost overhead. - I/O-bound work: threads often release the GIL while waiting (I/O, blocking syscalls or native libraries that call Py_BEGIN_ALLOW_THREADS), so many threads can overlap waiting and improve throughput/latency. - C extensions: native code can release the GIL, so libraries like NumPy, lxml, or parts of CPython I/O can run in parallel. Multiprocessing differences - multiprocessing uses separate OS processes; each process has its own Python interpreter and GIL, so CPU-bound tasks can run truly in parallel across cores. - Costs: higher memory use, process startup time, and IPC/serialization (pickling) overhead; more complex shared state. Practical guidance & trade-offs - Use threads (ThreadPoolExecutor or asyncio) for I/O-bound concurrency; low overhead, easy shared-memory use. - Use processes (ProcessPoolExecutor, multiprocessing) for CPU-bound tasks to utilize multiple cores. - Alternatives: write/reuse native extensions that release the GIL, use vectorized libraries (NumPy), or run on implementations without a GIL (Jython/IronPython) where appropriate. Example (pattern): from concurrent.futures import ThreadPoolExecutor, ProcessPoolExecutor # ThreadPoolExecutor for I/O; ProcessPoolExecutor for CPU-bound tasks. | V10: ## Python's GIL (Global Interpreter Lock) The GIL is a mutex in CPython that allows **only one thread to execute Python bytecode at a time**, even on multi-core machines. It exists to protect CPython's reference-counting memory management from race conditions. ### Impact on Multithreading - **CPU-bound work** gets no parallel speedup — threads take turns holding the GIL, so multiple threads can actually be *slower* than a single thread due to lock contention. - **I/O-bound work** benefits because the GIL is released during blocking I/O (network calls, file reads, `time.sleep`). Threads can overlap waiting, giving real concurrency. ```python # Good use of threading: concurrent HTTP requests with ThreadPoolExecutor(max_workers=10) as pool: results = pool.map(fetch_url, urls) ``` ### Impact on Multiprocessing - Each process gets its **own interpreter and GIL**, so CPU-bound work runs truly in parallel across cores. - The trade-off is **higher overhead**: process startup cost, memory duplication, and IPC serialization (pickle) for shared data. ```python # Good use of multiprocessing: CPU-heavy computation with ProcessPoolExecutor(max_workers=4) as pool: results = pool.map(crunch_numbers, datasets) ``` ### Quick Decision Guide | Workload | Use | Why | |---|---|---| | I/O-bound | `threading` / `asyncio` | GIL released during I/O; low overhead | | CPU-bound | `multiprocessing` | Bypasses GIL entirely | | Mixed | Combine both, or use `concurrent.futures` | Match strategy to bottleneck | **Note:** Python 3.13+ introduces an experimental free-threaded mode (`--disable-gil`) that removes the GIL entirely, enabling true thread-level parallelism for CPU-bound code — worth watching as it matures.
A11: 10 | B11: Python | C11: Show how to read a very large CSV in Python in chunks with pandas to limit memory use. | D11: 32.8 | E11: 176 | F11: 100 | G11: 6 | H11: 20 | I11: 100 | J11: 55 | K11: OK | L11: 14.6 | M11: 191 | N11: 100 | O11: 7 | P11: 100 | Q11: 100 | R11: 67 | S11: OK | T11: =IF(ABS(J11-R11)<=3,"Tie",IF(J11>R11,"Copilot","Claude")) -> Claude | U11: Approach - Use pandas.read_csv with chunksize to stream file in manageable DataFrame pieces. - Process each chunk and either (a) incrementally update aggregates, or (b) write filtered/transformed rows out to disk (CSV/HDF/parquet) to avoid accumulating data in memory. Why chunking helps - Only one chunk lives in memory at a time; overall memory stays bounded. - Good for aggregations, filters, ETL, or incremental writes. Not suitable for ops that require whole-file sort/merge unless using external algorithms. Example (incremental groupby, append results to file) ```python import os import pandas as pd dtypes = {'id': 'int32', 'category': 'category', 'value': 'float32'} chunksize = 100_000 reader = pd.read_csv('large.csv', usecols=['id','category','value'], dtype=dtypes, parse_dates=['date'], chunksize=chunksize, engine='c') out_path = 'category_sums.csv' if os.path.exists(out_path): os.remove(out_path) for i, chunk in enumerate(reader): chunk = chunk.dropna(subset=['category','value']) agg = chunk.groupby('category', observed=True)['value'].sum().reset_index() agg.to_csv(out_path, mode='a', index=False, header=(i==0)) ``` Tips & trade-offs - Set explicit dtypes and usecols to cut memory. Check chunk.memory_usage(deep=True).sum() for sizing. - Avoid pd.concat of all chunks; it defeats the purpose. - For more complex workloads or parallelism consider Dask, Vaex, or loading into a DB/Parquet for efficient queries. | V11: ## Reading Large CSVs in Chunks with Pandas Use the `chunksize` parameter in `pd.read_csv()` to iterate over the file in fixed-size row batches instead of loading it all at once: ```python import pandas as pd chunks = pd.read_csv("large_file.csv", chunksize=100_000) results = [] for chunk in chunks: # Process each chunk independently filtered = chunk[chunk["status"] == "active"] results.append(filtered) # Combine only the filtered results df = pd.concat(results, ignore_index=True) ``` **Key points:** - `chunksize=N` returns a `TextFileReader` iterator yielding DataFrames of N rows each. Memory usage stays proportional to the chunk size, not the file size. - **Aggregate without concatenating** when possible — if you only need a sum or mean, accumulate the result per chunk rather than collecting frames: ```python total = 0 for chunk in pd.read_csv("large_file.csv", chunksize=100_000): total += chunk["revenue"].sum() ``` - Pair with `usecols` and `dtype` to further cut memory: ```python pd.read_csv( "large_file.csv", chunksize=100_000, usecols=["id", "revenue", "status"], dtype={"id": "int32", "revenue": "float32", "status": "category"}, ) ``` **Trade-offs:** Chunked reading is simple and works everywhere, but for truly huge datasets (tens of GB+), consider **Polars** (`pl.scan_csv` with lazy evaluation) or **DuckDB** (`duckdb.read_csv`) which handle out-of-core processing more efficiently and with less boilerplate.
A12: 11 | B12: JavaScript/TypeScript | C12: Explain the JavaScript event loop, including microtasks and macrotasks. | D12: 21.9 | E12: 178 | F12: 100 | G12: 6 | H12: 20 | I12: 100 | J12: 55 | K12: OK | L12: 14.8 | M12: 218 | N12: 100 | O12: 6 | P12: 100 | Q12: 100 | R12: 67 | S12: OK | T12: =IF(ABS(J12-R12)<=3,"Tie",IF(J12>R12,"Copilot","Claude")) -> Claude | U12: Overview - The event loop runs JavaScript by repeatedly taking one "task" (macrotask), executing it, then draining all queued microtasks before the next macrotask. This keeps I/O/UI interleaved with small, high-priority jobs. Execution order (simplified) 1. Take one macrotask from the task queue (aka "task" — e.g., setTimeout, I/O, user events). 2. Execute it to completion. 3. Run all microtasks (Promise callbacks, queueMicrotask, MutationObserver) until none remain. 4. Perform rendering/paint (browser) then repeat. Key differences and Node quirks - Browsers: requestAnimationFrame ties to rendering; microtasks run before painting. - Node: process.nextTick runs even before Promise microtasks; setImmediate runs in the "check" phase (after I/O). Why it matters (practical) - Promise.then callbacks always run before setTimeout(..., 0). - Long macrotasks block the UI; use microtasks for short immediate work and macrotasks (or yielding) to keep UI responsive. - Excessive microtask scheduling can starve macrotasks and block rendering. Minimal example console.log('start'); setTimeout(()=>console.log('macrotask'),0); Promise.resolve().then(()=>console.log('promise')); queueMicrotask(()=>console.log('queueMicrotask')); console.log('end'); // Expected: start, end, promise, queueMicrotask, macrotask Trade-offs - Microtasks: fast, predictable, but can starve UI. - Macrotasks: safe for yielding, suitable for batching/cooperative multitasking. | V12: ## JavaScript Event Loop JavaScript is single-threaded. The **event loop** is the mechanism that lets it handle asynchronous work without blocking. ### How it works 1. **Call stack** — synchronous code executes here, one frame at a time. 2. **Task queues** — when async work completes, its callback is placed in a queue. The event loop picks tasks from these queues whenever the call stack is empty. ### Macrotasks vs. Microtasks **Macrotasks** (aka "tasks"): - `setTimeout`, `setInterval`, `setImmediate`, I/O callbacks, UI rendering events - One macrotask is picked per loop iteration. **Microtasks**: - `Promise.then/catch/finally`, `queueMicrotask`, `MutationObserver` - The **entire** microtask queue is drained after each macrotask (and after the initial script), before the next macrotask or any rendering. ### Execution order per loop tick 1. Execute the current macrotask (or initial script). 2. Drain all microtasks (including any microtasks they spawn). 3. Render updates (if needed, ~60 fps budget). 4. Pick the next macrotask. Repeat. ### Quick example ```js console.log('1'); // sync setTimeout(() => console.log('2'), 0); // macrotask Promise.resolve().then(() => console.log('3')); // microtask console.log('4'); // sync // Output: 1, 4, 3, 2 ``` ### Key takeaway Microtasks always jump the queue ahead of macrotasks. This is why a resolved promise callback fires before a `setTimeout(..., 0)`, and why an infinite microtask loop will starve rendering and timers entirely.
A13: 12 | B13: JavaScript/TypeScript | C13: What is the difference between let, const and var in JavaScript? | D13: 31.7 | E13: 83 | F13: 100 | G13: 6 | H13: 20 | I13: 100 | J13: 55 | K13: OK | L13: 14.2 | M13: 226 | N13: 100 | O13: 8 | P13: 100 | Q13: 100 | R13: 68 | S13: OK | T13: =IF(ABS(J13-R13)<=3,"Tie",IF(J13>R13,"Copilot","Claude")) -> Claude | U13: let vs const vs var - var - Function-scoped (or global), hoisted and initialized to undefined, can be redeclared and reassigned. - Example: console.log(a); // undefined; var a = 1; - let - Block-scoped, hoisted but uninitialized (Temporal Dead Zone) → ReferenceError if used before declaration. Mutable, cannot redeclare in same scope. - const - Block-scoped, TDZ applies, must be initialized, cannot be reassigned (but object/array contents remain mutable). Best practice: prefer const by default, use let when mutation is needed; avoid var. | V13: ## `var` vs `let` vs `const` ### Scope - **`var`** is **function-scoped** — it's visible throughout the entire function it's declared in, regardless of block boundaries. - **`let`** and **`const`** are **block-scoped** — they exist only within the nearest `{ }` block (if, for, while, etc.). ### Hoisting - All three are hoisted, but **`var`** is initialized to `undefined` at the top of its scope, so accessing it before its declaration returns `undefined`. - **`let`** and **`const`** are hoisted but **not initialized**, creating a **Temporal Dead Zone (TDZ)** — accessing them before declaration throws a `ReferenceError`. ### Reassignment & Redeclaration - **`var`** can be reassigned and redeclared in the same scope (silently, which is error-prone). - **`let`** can be reassigned but **not** redeclared in the same scope. - **`const`** cannot be reassigned or redeclared. Note: for objects/arrays, the *binding* is immutable but the contents are still mutable. ### Quick example ```js if (true) { var a = 1; let b = 2; const c = 3; } console.log(a); // 1 — var leaks out of the block console.log(b); // ReferenceError — let is block-scoped ``` ### Modern guidance - Default to **`const`** for values that won't be reassigned. - Use **`let`** when reassignment is needed. - Avoid **`var`** — its scoping and hoisting behavior is a common source of bugs. It exists mainly for legacy compatibility.
... A56: 55 | B56: Tech Writing | C56: Explain technical debt and how a team can manage it. | D56: 18.1 | E56: 254 | F56: 100 | G56: 7 | H56: 20 | I56: 100 | J56: 56 | K56: OK | L56: 14.3 | M56: 249 | N56: 100 | O56: 8 | P56: 100 | Q56: 100 | R56: 68 | S56: OK | T56: =IF(ABS(J56-R56)<=3,"Tie",IF(J56>R56,"Copilot","Claude")) -> Claude | U56: ## Technical Debt Explained **Technical debt** is the cost of postponing proper engineering work—shortcuts taken to ship faster that create future maintenance burdens. Like financial debt, it accumulates interest: every quick fix makes the codebase harder to modify, test, and understand. ### Common Sources - **Quick fixes** instead of proper solutions - **Outdated dependencies** left unupgraded - **Poor test coverage** from rushing to launch - **Duplicate code** that should be refactored - **Missing documentation** and unclear interfaces ### Why It Matters Unchecked debt slows teams down. Features take longer to build, bugs multiply, and turnover increases because new developers struggle with the codebase. ### Managing Technical Debt **1. Make it Visible** - Track debt in your backlog alongside features - Use checklists: missing tests, deprecated APIs, known workarounds - Assign story points so leadership understands the cost **2. Prioritize Ruthlessly** - Focus on high-impact items: dependencies in security patches, bottlenecks blocking new features, stability issues - Avoid perfectionism; not all debt needs repayment **3. Budget Regularly** - Reserve 20–30% of sprint capacity for debt reduction - Make it non-negotiable; debt compounds quickly without discipline **4. Pay Down Incrementally** - Refactor during feature work when you touch code - Break large efforts into smaller PRs - Use characterization tests to ensure behavior doesn't change **5. Prevent Accumulation** - Code review standards to catch shortcuts early - Automate testing and linting so standards are enforceable - Discuss trade-offs openly; some debt is intentional (temporary) The key: **balance shipping with sustainability**. Small, consistent investments beat crisis-driven rewrites. | V56: ## Technical Debt Technical debt is the implied cost of future rework caused by choosing a quick or expedient solution now instead of a better approach that would take longer. Like financial debt, it accumulates **interest** — the longer it sits, the more it slows down development. ### Common Sources - **Deliberate shortcuts** — "We'll clean this up after launch" - **Outdated design** — Architecture that hasn't evolved with requirements - **Lack of tests** — Makes changes risky and slow - **Copy-paste duplication** — Fixes must be applied in multiple places - **Dependency rot** — Stale libraries with security or compatibility issues ### How to Manage It 1. **Make it visible** — Track debt items in your backlog like any other work. If it's not tracked, it's ignored. 2. **Allocate capacity** — Reserve ~15–20% of each sprint for debt reduction. Don't wait for a "big rewrite" that never comes. 3. **Boy Scout Rule** — Leave code a little better than you found it. Small, incremental improvements compound over time. 4. **Prioritize by impact** — Pay down debt in high-churn areas first. Code that's rarely touched can wait. 5. **Prevent accumulation** — Code reviews, linting, CI checks, and clear coding standards reduce new debt at the source. ### Key Trade-off Some debt is **strategic** — shipping faster to validate a market hypothesis is rational. The problem isn't taking on debt; it's taking it on *unconsciously* or never paying it back. The goal is intentional, managed debt with a repayment plan.
